audioseal/__init__.py
audioseal/builder.py
audioseal/loader.py
audioseal/models.py
audioseal/py.typed
audioseal/cards/audioseal_detector_16bits.yaml
audioseal/cards/audioseal_wm_16bits.yaml
audioseal/libs/__init__.py
audioseal/libs/audiocraft/__init__.py
audioseal/libs/audiocraft/modules/__init__.py
audioseal/libs/audiocraft/modules/conv.py
audioseal/libs/audiocraft/modules/lstm.py
audioseal/libs/audiocraft/modules/seanet.py
audioseal-0.1.8.dist-info/licenses/LICENSE
audioseal-0.1.8.dist-info/WHEEL
audioseal-0.1.8.dist-info/METADATA
audioseal-0.1.8.dist-info/RECORD
