Metadata-Version: 2.4
Name: audioseal
Version: 0.1.8
Summary: Watermarking and detection for speech audios
Author: Facebook AI Research
Requires-Python: >=3.8
Classifier: License :: OSI Approved :: MIT License
Classifier: Topic :: Scientific/Engineering
Classifier: Development Status :: 4 - Beta
License-File: LICENSE
Requires-Dist: numpy
Requires-Dist: omegaconf
Requires-Dist: julius
Requires-Dist: torch>=1.13.0
Requires-Dist: func_argparse ; extra == "dev"
Requires-Dist: torchaudio ; extra == "dev"
Requires-Dist: soundfile ; extra == "dev"
Requires-Dist: pytest ; extra == "dev"
Requires-Dist: black ; extra == "dev"
Requires-Dist: isort ; extra == "dev"
Requires-Dist: flake8 ; extra == "dev"
Requires-Dist: pre-commit ; extra == "dev"
Project-URL: Source, https://github.com/facebookresearch/audioseal
Project-URL: Tracker, https://github.com/facebookresearch/audioseal/issues
Provides-Extra: dev
